Metadata-Version: 1.0
Name: scipion-em-ispyb
Version: 1.0.0
Summary: ISPyB monitor for scipion
Home-page: https://github.com/scipion-em/scipion-em-ispyb
Author: I2PC
Author-email: scipion@cnb.csic.es
License: UNKNOWN
Keywords: scipion cryoem imageprocessing scipion-1.2
Platform: UNKNOWN
